hmd_cli_librarian_sync_manager/__init__.py
hmd_cli_librarian_sync_manager/controller.py
hmd_cli_librarian_sync_manager/hmd_cli_librarian_sync_manager.py
hmd_cli_librarian_sync_manager/log.py
hmd_cli_librarian_sync_manager/config/__init__.py
hmd_cli_librarian_sync_manager/config/config_schema.json
hmd_cli_librarian_sync_manager/config/validate_config.py
hmd_cli_librarian_sync_manager/source_handlers/__init__.py
hmd_cli_librarian_sync_manager/source_handlers/librarian_sync_source.py
hmd_cli_librarian_sync_manager/source_handlers/manifest_source.py
hmd_cli_librarian_sync_manager/source_handlers/source.py
hmd_cli_librarian_sync_manager/telemetry/__init__.py
hmd_cli_librarian_sync_manager/telemetry/metrics.py
hmd_cli_librarian_sync_manager-1.0.158.dist-info/METADATA
hmd_cli_librarian_sync_manager-1.0.158.dist-info/WHEEL
hmd_cli_librarian_sync_manager-1.0.158.dist-info/top_level.txt
hmd_cli_librarian_sync_manager-1.0.158.dist-info/RECORD
