Metadata-Version: 2.1
Name: hmd-cli-librarian-sync-manager
Version: 1.0.158
Author: Adam Stortz
Author-email: adam.stortz@hmdlabs.io
License: unlicensed
Requires-Dist: acachecontrol==0.3.6
Requires-Dist: aenum==3.1.15
Requires-Dist: aiohappyeyeballs==2.4.3
Requires-Dist: aiohttp==3.10.10
Requires-Dist: aiosignal==1.3.1
Requires-Dist: alembic==1.13.3
Requires-Dist: anyio==3.7.1
Requires-Dist: async-timeout==4.0.3
Requires-Dist: attrs==24.2.0
Requires-Dist: aws-requests-auth==0.4.3
Requires-Dist: aws-secretsmanager-caching==1.1.3
Requires-Dist: awscrt==0.27.1
Requires-Dist: backoff==2.2.1
Requires-Dist: boto3==1.36.22
Requires-Dist: botocore==1.36.23
Requires-Dist: cachetools==5.2.0
Requires-Dist: cement==3.0.6
Requires-Dist: certifi==2025.4.26
Requires-Dist: cffi==2.0.0
Requires-Dist: charset-normalizer==2.0.12
Requires-Dist: colorlog==6.6.0
Requires-Dist: cryptography==46.0.2
Requires-Dist: decorator==5.2.1
Requires-Dist: durationpy==0.10
Requires-Dist: ecdsa==0.19.1
Requires-Dist: frozenlist==1.3.3
Requires-Dist: google-auth==2.9.1
Requires-Dist: googleapis-common-protos==1.70.0
Requires-Dist: greenlet==1.1.3.post0
Requires-Dist: gremlinpython==3.7.2
Requires-Dist: grpcio==1.75.1
Requires-Dist: hmd-cli-app~=1.2.616
Requires-Dist: hmd-cli-tools~=1.2.243
Requires-Dist: hmd-entity-storage~=0.2.315
Requires-Dist: hmd-graphql-client~=0.1.169
Requires-Dist: hmd-lang-librarian-sync~=0.1.20
Requires-Dist: hmd-lib-auth~=0.1.116
Requires-Dist: hmd-lib-librarian-client~=0.1.107
Requires-Dist: hmd-lib-telemetry~=0.1.51
Requires-Dist: hmd-meta-types~=0.2.94
Requires-Dist: hmd-schema-loader~=0.2.35
Requires-Dist: idna==3.10
Requires-Dist: importlib-metadata==8.7.0
Requires-Dist: inquirerpy==0.3.4
Requires-Dist: isodate==0.6.1
Requires-Dist: jinja2==3.1.6
Requires-Dist: jmespath==0.10.0
Requires-Dist: jsonschema==4.23.0
Requires-Dist: jsonschema-specifications==2024.10.1
Requires-Dist: kubernetes==34.1.0
Requires-Dist: mako==1.3.6
Requires-Dist: markupsafe==3.0.2
Requires-Dist: multidict==6.4.3
Requires-Dist: nest-asyncio==1.6.0
Requires-Dist: oauthlib==3.3.1
Requires-Dist: okta-jwt-verifier==0.3.0
Requires-Dist: opentelemetry-api==1.34.0
Requires-Dist: opentelemetry-exporter-otlp-proto-common==1.34.0
Requires-Dist: opentelemetry-exporter-otlp-proto-grpc==1.34.0
Requires-Dist: opentelemetry-exporter-otlp-proto-http==1.34.0
Requires-Dist: opentelemetry-instrumentation==0.55b0
Requires-Dist: opentelemetry-instrumentation-logging==0.55b0
Requires-Dist: opentelemetry-proto==1.34.0
Requires-Dist: opentelemetry-sdk==1.34.0
Requires-Dist: opentelemetry-semantic-conventions==0.55b0
Requires-Dist: packaging==25.0
Requires-Dist: pfzy==0.3.4
Requires-Dist: prompt-toolkit==3.0.38
Requires-Dist: protobuf==5.29.5
Requires-Dist: psutil==7.1.3
Requires-Dist: psycopg2-binary==2.9.10
Requires-Dist: pyasn1==0.6.1
Requires-Dist: pyasn1-modules==0.4.2
Requires-Dist: pycparser==2.23
Requires-Dist: pyjwt==2.10.1
Requires-Dist: python-dateutil==2.8.2
Requires-Dist: python-dotenv==1.1.1
Requires-Dist: python-jose==3.5.0
Requires-Dist: pyyaml==6.0.1
Requires-Dist: referencing==0.35.1
Requires-Dist: requests==2.32.3
Requires-Dist: requests-oauthlib==1.3.1
Requires-Dist: retry2==0.9.5
Requires-Dist: rpds-py==0.20.0
Requires-Dist: rsa==4.8
Requires-Dist: s3transfer==0.11.2
Requires-Dist: six==1.16.0
Requires-Dist: sniffio==1.3.1
Requires-Dist: sqlalchemy==2.0.36
Requires-Dist: typing-extensions==4.15.0
Requires-Dist: urllib3==1.26.8
Requires-Dist: watchfiles==1.1.1
Requires-Dist: wcwidth==0.2.6
Requires-Dist: websocket-client==1.3.3
Requires-Dist: wrapt==1.17.3
Requires-Dist: yarl==1.12.0
Requires-Dist: zipp==3.23.0
